excel_to_db/__init__.py
excel_to_db/cli.py
excel_to_db/config.py
excel_to_db/processor.py
excel_to_db/utils.py
excel_to_db-1.2.4.dist-info/LICENSE
excel_to_db-1.2.4.dist-info/METADATA
excel_to_db-1.2.4.dist-info/WHEEL
excel_to_db-1.2.4.dist-info/entry_points.txt
excel_to_db-1.2.4.dist-info/top_level.txt
excel_to_db-1.2.4.dist-info/RECORD
