Metadata-Version: 2.2
Name: excel-to-db
Version: 1.2.4
Summary: A tool for importing Excel files to MySQL database
Home-page: https://github.com/yourusername/excel_to_db
Author: Your Name
Author-email: Your Name <your.email@example.com>
License: MIT License
Project-URL: Homepage, https://github.com/yourusername/excel_to_db
Project-URL: Repository, https://github.com/yourusername/excel_to_db.git
Keywords: excel,mysql,database,import
Classifier: Programming Language :: Python :: 3
Classifier: License :: OSI Approved :: MIT License
Classifier: Operating System :: OS Independent
Requires-Python: >=3.6
License-File: LICENSE
Requires-Dist: pandas>=1.3.0
Requires-Dist: mysql-connector-python>=8.0.26
Requires-Dist: openpyxl>=3.0.7
Requires-Dist: tqdm>=4.62.0
Requires-Dist: click>=8.0.1
Requires-Dist: PyYAML>=5.4.1
Dynamic: author
Dynamic: description
Dynamic: description-content-type
Dynamic: home-page
Dynamic: requires-python
